<?xml version="1.0" encoding="UTF-8"?>
<beans xmlns="http://www.springframework.org/schema/beans" xmlns:xsi="http://www.w3.org/2001/XMLSchema-instance"
    xmlns:osgi="http://www.springframework.org/schema/osgi" xmlns:context="http://www.springframework.org/schema/context"
    xmlns:jaxrs="http://cxf.apache.org/jaxrs"
    xsi:schemaLocation="http://www.springframework.org/schema/beans
	 http://www.springframework.org/schema/beans/spring-beans.xsd
	 http://www.springframework.org/schema/context 
	 http://www.springframework.org/schema/context/spring-context.xsd
     http://cxf.apache.org/jaxrs http://cxf.apache.org/schemas/jaxrs.xsd">

    <!-- these are included in the dependency jar -->
    <import resource="classpath:META-INF/cxf/cxf.xml" />
    <import resource="classpath:META-INF/cxf/cxf-servlet.xml" />

    <!-- jar rest server registration -->
    <jaxrs:server id="restContainer" address="/">
        <!-- registering beans -->
        <jaxrs:serviceBeans>
            <ref bean="nslcmSvcRoaResource"></ref>
        </jaxrs:serviceBeans>
        <!-- registering providers -->
        <jaxrs:providers>
            <bean class="org.codehaus.jackson.jaxrs.JacksonJsonProvider" />
        </jaxrs:providers>
    </jaxrs:server>

    <bean id="nslcmSvcRoaResource" class="org.openo.sdno.nslcm.rest.NslcmSvcRoaResource">
        <property name="dbOper" ref="dbOper"></property>
        <property name="nslcmService" ref="nslcmService"></property>
    </bean>

    <bean id="dbOper" class="org.openo.sdno.nslcm.util.db.DbOper">
    </bean>

    <bean id="nslcmService" class="org.openo.sdno.nslcm.service.impl.NslcmServiceImpl">
        <property name="dbOper" ref="dbOper"></property>
        <property name="catalogSbiService" ref="catalogSbiService"></property>
        <property name="overlaySbiService" ref="overlaySbiService"></property>
        <property name="underlaySbiService" ref="underlaySbiService"></property>
    </bean>

    <bean id="catalogSbiService" class="org.openo.sdno.nslcm.sbi.impl.CatalogSbiServiceImpl">
    </bean>


    <bean id="overlaySbiService" class="org.openo.sdno.nslcm.sbi.impl.OverlaySbiServiceImpl">
    </bean>

    <bean id="underlaySbiService" class="org.openo.sdno.nslcm.sbi.impl.UnderlaySbiServiceImpl">
    </bean>

    <bean id="nslcmRestModule" class="org.openo.sdno.nslcm.NslcmRestModule" init-method="init" destroy-method="destroy">
    </bean>

</beans>
